hupa/__init__.py
hupa_voicedb-0.1.1.dist-info/LICENSE
hupa_voicedb-0.1.1.dist-info/METADATA
hupa_voicedb-0.1.1.dist-info/WHEEL
hupa_voicedb-0.1.1.dist-info/top_level.txt
hupa_voicedb-0.1.1.dist-info/RECORD
