Metadata-Version: 2.1
Name: hupa-voicedb
Version: 0.1.1
Summary: Príncipe de Asturias Hospital Voice Disorders Database Reader module
License: GPL-2.0 License
Project-URL: Repository, https://github.com/tikuma-lsuhsc/python-hupa-voicedb/issues
Project-URL: Issues, https://github.com/tikuma-lsuhsc/python-hupa-voicedb/issues
Project-URL: Pull_Requests, https://github.com/tikuma-lsuhsc/python-hupa-voicedb/pulls
Keywords: multimedia
Classifier: Development Status :: 4 - Beta
Classifier: License :: OSI Approved :: GNU General Public License v2 (GPLv2)
Classifier: Topic :: Multimedia :: Sound/Audio
Classifier: Programming Language :: Python :: 3
Requires-Python: >=3.8
License-File: LICENSE
Requires-Dist: pandas
Requires-Dist: numpy
Requires-Dist: xlrd
